odoo9_addon_account_banking_fr_lcr-9.0.1.0.0.99.dev15-py2.7-nspkg.pth
odoo9_addon_account_banking_fr_lcr-9.0.1.0.0.99.dev15.dist-info/METADATA
odoo9_addon_account_banking_fr_lcr-9.0.1.0.0.99.dev15.dist-info/RECORD
odoo9_addon_account_banking_fr_lcr-9.0.1.0.0.99.dev15.dist-info/WHEEL
odoo9_addon_account_banking_fr_lcr-9.0.1.0.0.99.dev15.dist-info/namespace_packages.txt
odoo9_addon_account_banking_fr_lcr-9.0.1.0.0.99.dev15.dist-info/top_level.txt
odoo_addons/account_banking_fr_lcr/README.rst
odoo_addons/account_banking_fr_lcr/__init__.py
odoo_addons/account_banking_fr_lcr/__openerp__.py
odoo_addons/account_banking_fr_lcr/post_install.py
odoo_addons/account_banking_fr_lcr/data/account_payment_method.xml
odoo_addons/account_banking_fr_lcr/demo/lcr_demo.xml
odoo_addons/account_banking_fr_lcr/i18n/ca.po
odoo_addons/account_banking_fr_lcr/i18n/de.po
odoo_addons/account_banking_fr_lcr/i18n/es.po
odoo_addons/account_banking_fr_lcr/i18n/fi.po
odoo_addons/account_banking_fr_lcr/i18n/fr.po
odoo_addons/account_banking_fr_lcr/i18n/nb_NO.po
odoo_addons/account_banking_fr_lcr/models/__init__.py
odoo_addons/account_banking_fr_lcr/models/account_move_line.py
odoo_addons/account_banking_fr_lcr/models/account_payment_order.py
odoo_addons/account_banking_fr_lcr/static/description/icon.png
